{
  "comments": [
    {
      "id": 1,
      "body": "some comment",
      "postId": 1
    }
  ],
  "logins": [
    {
      "id": "10158391210175051",
      "name": "Dmytro Yurchenko"
    }
  ],
  "localizations": [],
  "recommendations": [],
  "products": [
    {
      "id": 1,
      "name": "Rustmesser VICTORINOX",
      "price": 1.55,
      "discount": 0.5,
      "picture": "http://localhost:3000/assets/product1.png",
      "reviewIds": [
        1,
        2
      ],
      "sentimentIds": [
        1,
        2
      ]
    },
    {
      "id": 2,
      "name": "Tadelmesser BASIC",
      "price": 1.4,
      "discount": 0.5,
      "picture": "http://localhost:3000/assets/product2.png",
      "reviewIds": [
        1,
        2
      ],
      "sentimentIds": [
        1,
        2
      ]
    },
    {
      "id": 3,
      "name": "Kaffeeloffel ROSSO",
      "price": 1.45,
      "discount": 0.5,
      "picture": "http://localhost:3000/assets/product3.png",
      "reviewIds": [
        3
      ],
      "sentimentIds": [
        3
      ]
    },
    {
      "id": 4,
      "name": "Kuchen-/ Geflugelschere",
      "price": 7.4,
      "discount": 0.5,
      "picture": "http://localhost:3000/assets/product4.png",
      "reviewIds": [
        3
      ],
      "sentimentIds": [
        3
      ]
    },
    {
      "id": 5,
      "name": "Kaffeeloffel PRIMO",
      "price": 0.45,
      "discount": 0.5,
      "picture": "http://localhost:3000/assets/product5.png",
      "reviewIds": [
        4
      ],
      "sentimentIds": []
    },
    {
      "id": 6,
      "name": "Pepsi",
      "price": 11,
      "discount": 0.5,
      "picture": "http://localhost:3000/assets/product6.png",
      "reviewIds": [
        4
      ],
      "sentimentIds": []
    }
  ],
  "purchases": [
    {
      "id": 1,
      "userId": 1,
      "productId": 3,
      "lat": 47.3769,
      "lng": 8.5417
    },
    {
      "id": 2,
      "userId": 2,
      "productId": 2,
      "lat": 47.3369,
      "lng": 8.5447
    },
    {
      "id": 3,
      "userId": 2,
      "productId": 3,
      "lat": 47.2769,
      "lng": 8.3417
    },
    {
      "id": 4,
      "userId": 2,
      "productId": 3,
      "lat": 47.3269,
      "lng": 8.5437
    },
    {
      "id": 5,
      "userId": 1,
      "productId": 2,
      "lat": 46.3769,
      "lng": 8.3417
    },
    {
      "id": 5,
      "userId": 1,
      "productId": 2,
      "lat": 47.3769,
      "lng": 8.3
    },
    {
      "id": 6,
      "userId": 3,
      "productId": 3,
      "lat": 47.3769,
      "lng": 8.3
    },
    {
      "id": 7,
      "userId": 1,
      "productId": 5,
      "lat": 47.3769,
      "lng": 8.3
    },
    {
      "id": 8,
      "userId": 4,
      "productId": 5,
      "lat": 47.5769,
      "lng": 8.2
    },
    {
      "id": 9,
      "userId": 4,
      "productId": 5,
      "lat": 47.3769,
      "lng": 8.2
    }
  ],
  "sentiments": [
    {
      "id": 1,
      "text": "Awesome",
      "sentiment": "good",
      "lang": "de",
      "productId": 1
    },
    {
      "id": 2,
      "text": "Not that great",
      "lang": "en",
      "sentiment": "bad",
      "productId": 1
    },
    {
      "lang": "en",
      "text": "Awesome this product is jsut great, grusig",
      "productId": 1,
      "sentiment": "good",
      "id": 4
    },
    {
      "lang": "de",
      "text": "Das is super gut",
      "productId": 1,
      "sentiment": "good",
      "id": 5
    },
    {
      "lang": "de",
      "text": "Nicht grusig, shiaisse",
      "productId": 1,
      "sentiment": "bad",
      "id": 6
    },
    {
      "lang": "en",
      "text": "those knives are sharp one of best I have ever use keep up the good work",
      "productId": "1",
      "sentiment": "good",
      "id": 7
    },
    {
      "lang": "en",
      "text": "those knives are sharp one of best I have ever use keep up the good work",
      "productId": "1",
      "sentiment": "good",
      "id": 8
    },
    {
      "lang": "en",
      "text": "those knives are sharp one of best I have ever use keep up the good work",
      "productId": "1",
      "sentiment": "good",
      "id": 9
    },
    {
      "lang": "en",
      "text": "those knives are sharp one of best I have ever use keep up the good work",
      "productId": "1",
      "sentiment": "good",
      "id": 10
    }
  ],
  "voice-recognitions": [
    {
      "id": 1,
      "text": "This product is awesome!"
    }
  ],
  "reviews": [
    {
      "id": 1,
      "author": "Amazing Jeff",
      "userId": 1,
      "review": "This product is awesome!",
      "sentiment": "good",
      "productId": 1,
      "stars": 4
    },
    {
      "id": 2,
      "author": "Amazing Juice",
      "userId": 2,
      "review": "This product is more awesome!",
      "sentiment": "good",
      "productId": 1,
      "stars": 4
    }
  ],
  "users": [
    {
      "id": 1,
      "name": "Amazing Jeff",
      "friendsIds": [
        1,
        2,
        3
      ]
    },
    {
      "id": 2,
      "firstName": "Kale",
      "lastName": "Jaylon",
      "phoneNumber": "265-060-7439",
      "friends": []
    },
    {
      "id": 3,
      "firstName": "Tevin",
      "lastName": "Nedra",
      "phoneNumber": "622-714-9599",
      "friends": [
        3,
        4
      ]
    },
    {
      "id": 4,
      "firstName": "Ressie",
      "lastName": "Jana",
      "phoneNumber": "128-281-1100",
      "friends": [
        1,
        2
      ]
    }
  ]
}